dendroplot/__init__.py
dendroplot/run_dendro.py
dendroplot/analysis/__init__.py
dendroplot/analysis/calc_phys_props.py
dendroplot/analysis/define_asgn.py
dendroplot/analysis/eqres.py
dendroplot/analysis/find_clusters.py
dendroplot/analysis/get_response_width.py
dendroplot/analysis/noisegen.py
dendroplot/lte/__init__.py
dendroplot/lte/add_ltemass.py
dendroplot/lte/lte.py
dendroplot/plotting/__init__.py
dendroplot/plotting/colorcode.py
dendroplot/plotting/comp_props.py
dendroplot/plotting/dendro_volume_3d.py
dendroplot/plotting/hist1d.py
dendroplot/plotting/histplot.py
dendroplot/plotting/inspect_flux.py
dendroplot/plotting/inspect_tclean.py
dendroplot/plotting/mass_spec.py
dendroplot/plotting/mom0plot.py
dendroplot/plotting/pltprops.py
dendroplot/plotting/prop_hist.py
dendroplot/plotting/yso_postage_stamp.py
dendroplot-0.7.0.dist-info/LICENSE
dendroplot-0.7.0.dist-info/METADATA
dendroplot-0.7.0.dist-info/WHEEL
dendroplot-0.7.0.dist-info/top_level.txt
dendroplot-0.7.0.dist-info/RECORD
