Metadata-Version: 2.1
Name: dendroplot
Version: 0.7.0
Summary: Helper tasks for astrodendro
Home-page: https://github.com/tonywong94/dendroplot
Download-URL: https://github.com/tonywong94/dendroplot/archive/refs/tags/v0.5.0.tar.gz
Author: Tony Wong
Author-email: tonywong94@gmail.com
License-File: LICENSE
Requires-Dist: numpy
Requires-Dist: scipy
Requires-Dist: astropy
Requires-Dist: radio-beam
Requires-Dist: spectral-cube
Requires-Dist: astrodendro
